setup.py
diveinto/__init__.py
diveinto/db_controller.py
diveinto/element.py
diveinto.egg-info/PKG-INFO
diveinto.egg-info/SOURCES.txt
diveinto.egg-info/dependency_links.txt
diveinto.egg-info/top_level.txt