Metadata-Version: 1.0
Name: diveinto
Version: 0.3.1
Summary: Task manager
Home-page: https://github.com/paragraph14/diveinto
Author: chu
Author-email: they.know.who.is.the.strongest@gmail.com
License: MIT
Platform: UNKNOWN
